pypic/__init__.py
pypic-0.1.0.dist-info/LICENSE
pypic-0.1.0.dist-info/WHEEL
pypic-0.1.0.dist-info/METADATA
pypic-0.1.0.dist-info/RECORD
