Metadata-Version: 1.2
Name: pypic
Version: 0.1.0
Summary: Compare pypi packages
Home-page: https://github.com/ebukari/pypic
License: UNKNOWN
Author: Ezekiel N. Bukari(Charitoo Dunamis)
Author-email: charitoodunamis@gmail.com
Classifier: License :: OSI Approved :: GNU General Public License v3 or later (GPLv3+)
